nlpt/preprocess.py
nlpt-0.0.3.dist-info/METADATA
nlpt-0.0.3.dist-info/WHEEL
nlpt-0.0.3.dist-info/top_level.txt
nlpt-0.0.3.dist-info/RECORD
